[
    {
        "id": "1",
        "title": "Online Skype Quran Classes",
        "taka": "50$",
        "p": "Our Quran classes offer flexible and customized learning opportunities for busy adults…",
        "img": "https://wi.wallpapertip.com/wsimgs/73-738269_girl-cartoon-with-hijab.jpg"
    },
    {
        "id": "2",
        "title": "Online Quran Teaching at Home",
        "taka": "50$",
        "p": "Our Quran classes offer flexible and customized learning opportunities for busy adults…",
        "img": "https://wi.wallpapertip.com/wsimgs/73-738269_girl-cartoon-with-hijab.jpg"
    },
    {
        "id": "3",
        "title": "Quran Classes for Kids",
        "taka": "50$",
        "p": "Our Quran classes offer flexible and customized learning opportunities for busy adults…",
        "img": "https://wi.wallpapertip.com/wsimgs/73-738269_girl-cartoon-with-hijab.jpg"
    },
    {
        "id": "4",
        "title": "Learn Quran with Tajweed",
        "taka": "50$",
        "p": "Our Quran classes offer flexible and customized learning opportunities for busy adults…",
        "img": "https://wi.wallpapertip.com/wsimgs/73-738269_girl-cartoon-with-hijab.jpg"
    },
    {
        "id": "5",
        "title": "Quran Courses for Females",
        "taka": "50$",
        "p": "Our Quran classes offer flexible and customized learning opportunities for busy adults…",
        "img": "https://wi.wallpapertip.com/wsimgs/73-738269_girl-cartoon-with-hijab.jpg"
    },
    {
        "id": "6",
        "title": "Quran Foundation (Basic Tajweed)",
        "taka": "50$",
        "p": "Our Quran classes offer flexible and customized learning opportunities for busy adults…",
        "img": "https://wi.wallpapertip.com/wsimgs/73-738269_girl-cartoon-with-hijab.jpg"
    },
    {
        "id": "7",
        "title": "Online Quran Classes for Adults",
        "taka": "50$",
        "p": "Our Quran classes offer flexible and customized learning opportunities for busy adults…",
        "img": "https://wi.wallpapertip.com/wsimgs/73-738269_girl-cartoon-with-hijab.jpg"
    }
]